MANIFEST.in
README.md
requirements.txt
setup.py
merkletools/__init__.py
merkletools.egg-info/PKG-INFO
merkletools.egg-info/SOURCES.txt
merkletools.egg-info/dependency_links.txt
merkletools.egg-info/not-zip-safe
merkletools.egg-info/requires.txt
merkletools.egg-info/top_level.txt
tests/__init__.py
tests/test_merkle_tools.py