Metadata-Version: 1.1
Name: merkletools
Version: 1.0.3
Summary: Merkle Tools
Home-page: https://github.com/Tierion/pymerkletools
Author: Eder Santana
Author-email: UNKNOWN
License: MIT
Keywords: merkle tree,blockchain,tierion
Platform: UNKNOWN
Classifier: Intended Audience :: Developers
Classifier: Intended Audience :: Education
Classifier: Intended Audience :: Science/Research
Classifier: License :: OSI Approved :: MIT License
Classifier: Programming Language :: Python :: 2.7
Classifier: Programming Language :: Python :: 3.6
Classifier: Topic :: Software Development :: Libraries
Classifier: Topic :: Software Development :: Libraries :: Python Modules
